useenv/__init__.py
useenv-0.5.1.dist-info/METADATA
useenv-0.5.1.dist-info/WHEEL
useenv-0.5.1.dist-info/entry_points.txt
useenv-0.5.1.dist-info/RECORD
