Metadata-Version: 2.1
Name: useenv
Version: 0.5.1
Summary: 
Author: Your Name
Author-email: you@example.com
Requires-Python: >=3.10,<4.0
Classifier: Programming Language :: Python :: 3
Classifier: Programming Language :: Python :: 3.10
Classifier: Programming Language :: Python :: 3.11
Requires-Dist: pyyaml (>=6.0.1,<7.0.0)
Requires-Dist: typer (>=0.9.0,<0.10.0)
